.gitignore
Makefile
README.rst
setup.py
cyrusbus/__init__.py
cyrusbus/bus.py
cyrusbus.egg-info/PKG-INFO
cyrusbus.egg-info/SOURCES.txt
cyrusbus.egg-info/dependency_links.txt
cyrusbus.egg-info/top_level.txt
tests/__init__.py
tests/test_bus.py