Metadata-Version: 1.0
Name: cyrusbus
Version: 0.1.0
Summary: cyrusbus - Dead simple event bus for python apps
Home-page: http://github.com/heynemann/cyrusbus
Author: Bernardo Heynemann
Author-email: heynemann@gmail.com
License: OSI
Keywords: message bus event python
Platform: UNKNOWN
Classifier: Development Status :: 5 - Production/Stable
Classifier: Intended Audience :: Developers
